odoo/addons/website_sale_resource_booking/README.rst
odoo/addons/website_sale_resource_booking/__init__.py
odoo/addons/website_sale_resource_booking/__manifest__.py
odoo/addons/website_sale_resource_booking/controllers/__init__.py
odoo/addons/website_sale_resource_booking/controllers/main.py
odoo/addons/website_sale_resource_booking/data/ir_cron_data.xml
odoo/addons/website_sale_resource_booking/demo/assets.xml
odoo/addons/website_sale_resource_booking/i18n/es.po
odoo/addons/website_sale_resource_booking/i18n/website_sale_resource_booking.pot
odoo/addons/website_sale_resource_booking/models/__init__.py
odoo/addons/website_sale_resource_booking/models/product_template.py
odoo/addons/website_sale_resource_booking/models/resource_booking.py
odoo/addons/website_sale_resource_booking/models/sale_order.py
odoo/addons/website_sale_resource_booking/models/sale_order_line.py
odoo/addons/website_sale_resource_booking/readme/CONTRIBUTORS.rst
odoo/addons/website_sale_resource_booking/readme/DESCRIPTION.rst
odoo/addons/website_sale_resource_booking/readme/INSTALL.rst
odoo/addons/website_sale_resource_booking/readme/USAGE.rst
odoo/addons/website_sale_resource_booking/static/description/icon.png
odoo/addons/website_sale_resource_booking/static/description/index.html
odoo/addons/website_sale_resource_booking/static/src/css/website_sale_resource_booking.scss
odoo/addons/website_sale_resource_booking/static/src/js/tour_checkout.js
odoo/addons/website_sale_resource_booking/templates/assets.xml
odoo/addons/website_sale_resource_booking/templates/website_sale.xml
odoo/addons/website_sale_resource_booking/tests/__init__.py
odoo/addons/website_sale_resource_booking/tests/test_ui.py
odoo/addons/website_sale_resource_booking/views/product_template_view.xml
odoo12_addon_website_sale_resource_booking-12.0.1.0.1.dist-info/METADATA
odoo12_addon_website_sale_resource_booking-12.0.1.0.1.dist-info/WHEEL
odoo12_addon_website_sale_resource_booking-12.0.1.0.1.dist-info/top_level.txt
odoo12_addon_website_sale_resource_booking-12.0.1.0.1.dist-info/RECORD
